LICENSE
NOTICE.txt
README.md
setup.cfg
setup.py
document_transformers.egg-info/PKG-INFO
document_transformers.egg-info/SOURCES.txt
document_transformers.egg-info/dependency_links.txt
document_transformers.egg-info/requires.txt
document_transformers.egg-info/top_level.txt
sentence_transformers/LoggingHandler.py
sentence_transformers/SentenceTransformer.py
sentence_transformers/__init__.py
sentence_transformers/model_card_templates.py
sentence_transformers/util.py
sentence_transformers/cross_encoder/CrossEncoder.py
sentence_transformers/cross_encoder/__init__.py
sentence_transformers/cross_encoder/evaluation/CEBinaryAccuracyEvaluator.py
sentence_transformers/cross_encoder/evaluation/CEBinaryClassificationEvaluator.py
sentence_transformers/cross_encoder/evaluation/CECorrelationEvaluator.py
sentence_transformers/cross_encoder/evaluation/CERerankingEvaluator.py
sentence_transformers/cross_encoder/evaluation/CESoftmaxAccuracyEvaluator.py
sentence_transformers/cross_encoder/evaluation/__init__.py
sentence_transformers/datasets/DenoisingAutoEncoderDataset.py
sentence_transformers/datasets/NoDuplicatesDataLoader.py
sentence_transformers/datasets/ParallelSentencesDataset.py
sentence_transformers/datasets/SentenceLabelDataset.py
sentence_transformers/datasets/SentencesDataset.py
sentence_transformers/datasets/__init__.py
sentence_transformers/evaluation/BinaryClassificationEvaluator.py
sentence_transformers/evaluation/EmbeddingSimilarityEvaluator.py
sentence_transformers/evaluation/InformationRetrievalEvaluator.py
sentence_transformers/evaluation/LabelAccuracyEvaluator.py
sentence_transformers/evaluation/MSEEvaluator.py
sentence_transformers/evaluation/MSEEvaluatorFromDataFrame.py
sentence_transformers/evaluation/ParaphraseMiningEvaluator.py
sentence_transformers/evaluation/RerankingEvaluator.py
sentence_transformers/evaluation/SentenceEvaluator.py
sentence_transformers/evaluation/SequentialEvaluator.py
sentence_transformers/evaluation/SimilarityFunction.py
sentence_transformers/evaluation/TranslationEvaluator.py
sentence_transformers/evaluation/TripletEvaluator.py
sentence_transformers/evaluation/__init__.py
sentence_transformers/losses/BatchAllTripletLoss.py
